to_tty.py
to_tty-1.0.dist-info/METADATA
to_tty-1.0.dist-info/WHEEL
to_tty-1.0.dist-info/entry_points.txt
to_tty-1.0.dist-info/top_level.txt
to_tty-1.0.dist-info/RECORD
